kuhl_haus/canary/__init__.py
kuhl_haus/canary/app.py
kuhl_haus/canary/env.py
kuhl_haus/canary/handlers.py
kuhl_haus/canary/helpers/__init__.py
kuhl_haus/canary/helpers/canary_configs.py
kuhl_haus/canary/models/__init__.py
kuhl_haus/canary/models/canary_script.py
kuhl_haus/canary/models/dns_resolver.py
kuhl_haus/canary/models/endpoint_model.py
kuhl_haus/canary/scripts/__init__.py
kuhl_haus/canary/scripts/canary.py
kuhl_haus/canary/scripts/script.py
kuhl_haus/canary/tasks/__init__.py
kuhl_haus/canary/tasks/dns_check.py
kuhl_haus/canary/tasks/http_health_check.py
kuhl_haus/canary/tasks/tls.py
kuhl_haus_canary-0.2.18.dist-info/METADATA
kuhl_haus_canary-0.2.18.dist-info/WHEEL
kuhl_haus_canary-0.2.18.dist-info/entry_points.txt
kuhl_haus_canary-0.2.18.dist-info/licenses/LICENSE.txt
kuhl_haus_canary-0.2.18.dist-info/RECORD
