Metadata-Version: 2.1
Name: kuhl-haus-canary
Version: 0.2.18
Summary: Simple canary and site monitoring service
Author-Email: Tom Pounders <git@oldschool.engineer>
License: The MIT License (MIT)
Classifier: Development Status :: 4 - Beta
Classifier: Programming Language :: Python
Project-URL: Homepage, https://github.com/kuhl-haus/kuhl-haus-canary
Project-URL: Documentation, https://github.com/kuhl-haus/kuhl-haus-canary/wiki
Project-URL: Source, https://github.com/kuhl-haus/kuhl-haus-canary.git
Project-URL: Changelog, https://github.com/kuhl-haus/kuhl-haus-canary/commits
Project-URL: Tracker, https://github.com/kuhl-haus/kuhl-haus-canary/issues
Requires-Python: >=3.12
Requires-Dist: kuhl-haus-metrics
Requires-Dist: requests
Requires-Dist: dataclasses-json
Requires-Dist: dnspython
Requires-Dist: pyOpenSSL
Requires-Dist: importlib-metadata
Provides-Extra: testing
Requires-Dist: setuptools; extra == "testing"
Requires-Dist: pdm-backend; extra == "testing"
Requires-Dist: pytest; extra == "testing"
Requires-Dist: pytest-cov; extra == "testing"
